<?xml version='1.0' encoding='utf-8'?>
<compendium version="5" auto_indent="NO">
  <spell>
    <name>Guidance [2024]</name>
    <classes>Sorcerer (Mage of Quandrix), Wizard (Mage of Quandrix)</classes>
  </spell>
  <spell>
    <name>Guiding Bolt [2024]</name>
    <classes>Sorcerer (Mage of Quandrix), Wizard (Mage of Quandrix)</classes>
  </spell>
  <spell>
    <name>Enlarge/Reduce [2024]</name>
    <classes>Sorcerer (Mage of Quandrix), Wizard (Mage of Quandrix)</classes>
  </spell>
  <spell>
    <name>Spike Growth [2024]</name>
    <classes>Sorcerer (Mage of Quandrix), Wizard (Mage of Quandrix)</classes>
  </spell>
  <spell>
    <name>Aura of Vitality [2024]</name>
    <classes>Sorcerer (Mage of Quandrix), Wizard (Mage of Quandrix)</classes>
  </spell>
  <spell>
    <name>Haste [2024]</name>
    <classes>Sorcerer (Mage of Quandrix), Wizard (Mage of Quandrix)</classes>
  </spell>
  <spell>
    <name>Control Water [2024]</name>
    <classes>Sorcerer (Mage of Quandrix), Wizard (Mage of Quandrix)</classes>
  </spell>
  <spell>
    <name>Freedom of Movement [2024]</name>
    <classes>Sorcerer (Mage of Quandrix), Wizard (Mage of Quandrix)</classes>
  </spell>
  <spell>
    <name>Circle of Power [2024]</name>
    <classes>Sorcerer (Mage of Quandrix), Wizard (Mage of Quandrix)</classes>
  </spell>
  <spell>
    <name>Passwall [2024]</name>
    <classes>Sorcerer (Mage of Quandrix), Wizard (Mage of Quandrix)</classes>
  </spell>

  <spell>
    <name>Sacred Flame [2024]</name>
    <classes>Bard (Mage of Lorehold), Warlock (Mage of Lorehold), Wizard (Mage of Lorehold)</classes>
  </spell>
  <spell>
    <name>Comprehend Languages [2024]</name>
    <classes>Bard (Mage of Lorehold), Warlock (Mage of Lorehold), Wizard (Mage of Lorehold)</classes>
  </spell>
  <spell>
    <name>Knock [2024]</name>
    <classes>Bard (Mage of Lorehold), Warlock (Mage of Lorehold), Wizard (Mage of Lorehold)</classes>
  </spell>
  <spell>
    <name>Locate Object [2024]</name>
    <classes>Bard (Mage of Lorehold), Warlock (Mage of Lorehold), Wizard (Mage of Lorehold)</classes>
  </spell>
  <spell>
    <name>Speak With Dead [2024]</name>
    <classes>Bard (Mage of Lorehold), Warlock (Mage of Lorehold), Wizard (Mage of Lorehold)</classes>
  </spell>
  <spell>
    <name>Spirit Guardians [2024]</name>
    <classes>Bard (Mage of Lorehold), Warlock (Mage of Lorehold), Wizard (Mage of Lorehold)</classes>
  </spell>
  <spell>
    <name>Arcane Eye [2024]</name>
    <classes>Bard (Mage of Lorehold), Warlock (Mage of Lorehold), Wizard (Mage of Lorehold)</classes>
  </spell>
  <spell>
    <name>Stone Shape [2024]</name>
    <classes>Bard (Mage of Lorehold), Warlock (Mage of Lorehold), Wizard (Mage of Lorehold)</classes>
  </spell>
  <spell>
    <name>Destructive Wave [2024]</name>
    <classes>Bard (Mage of Lorehold), Warlock (Mage of Lorehold), Wizard (Mage of Lorehold)</classes>
  </spell>
  <spell>
    <name>Legend Lore [2024]</name>
    <classes>Bard (Mage of Lorehold), Warlock (Mage of Lorehold), Wizard (Mage of Lorehold)</classes>
  </spell>

  <spell>
    <name>Spare the Dying [2024]</name>
    <classes>Druid (Mage of Witherbloom), Warlock (Mage of Witherbloom)</classes>
  </spell>
  <spell>
    <name>Cure Wounds [2024]</name>
    <classes>Druid (Mage of Witherbloom), Warlock (Mage of Witherbloom)</classes>
  </spell>
  <spell>
    <name>Inflict Wounds [2024]</name>
    <classes>Druid (Mage of Witherbloom), Warlock (Mage of Witherbloom)</classes>
  </spell>
  <spell>
    <name>Lesser Restoration [2024]</name>
    <classes>Druid (Mage of Witherbloom), Warlock (Mage of Witherbloom)</classes>
  </spell>
  <spell>
    <name>Ray of Enfeeblement [2024]</name>
    <classes>Druid (Mage of Witherbloom), Warlock (Mage of Witherbloom)</classes>
  </spell>
  <spell>
    <name>Revivify [2024]</name>
    <classes>Druid (Mage of Witherbloom), Warlock (Mage of Witherbloom)</classes>
  </spell>
  <spell>
    <name>Vampiric Touch [2024]</name>
    <classes>Druid (Mage of Witherbloom), Warlock (Mage of Witherbloom)</classes>
  </spell>
  <spell>
    <name>Blight [2024]</name>
    <classes>Druid (Mage of Witherbloom), Warlock (Mage of Witherbloom)</classes>
  </spell>
  <spell>
    <name>Greater Restoration [2024]</name>
    <classes>Druid (Mage of Witherbloom), Warlock (Mage of Witherbloom)</classes>
  </spell>
  <spell>
    <name>Antilife Shell [2024]</name>
    <classes>Druid (Mage of Witherbloom), Warlock (Mage of Witherbloom)</classes>
  </spell>
  <spell>
    <name>Mass Cure Wounds [2024]</name>
    <classes>Druid (Mage of Witherbloom), Warlock (Mage of Witherbloom)</classes>
  </spell>
</compendium>