<?xml version='1.0' encoding='utf-8'?>
<compendium version="5" auto_indent="NO">
<monster xmlns:exsl="http://exslt.org/common">
		<name>Space Hamster (WD)</name>
		<size>T</size>
		<type>beast</type>
		<alignment>unaligned</alignment>
		<ac>10</ac>
		<hp>1 (1d4 - 1)</hp>
		<speed>20 ft.</speed>
		<str>2</str><dex>11</dex><con>9</con><int>2</int><wis>10</wis><cha>4</cha>
		<save/>
		<skill/>
		<resist/>
		<vulnerable/>
		<immune/>
		<conditionImmune/>
		<senses>darkvision 30 ft.</senses>
		<passive>10</passive>
		<languages/>
		<cr>0</cr>
		<trait>
			<name>Source</name>
			<text>Waterdeep: Dungeon of the Mad Mage p. 251</text>
		</trait>
		<trait>
			<name>Keen Smell</name>
			<text>the hamster has advantage on Wisdom (Perception) checks that rely on smell.</text>
		</trait>
	</monster>
</compendium>